{"name":"Japanno-to","tagline":"a memo at japanese","body":"# 吃胖筆記本 ジャパンノート (Japan No-To)\r\n===========\r\na memo at japanese\r\n\r\n##Concept\r\n\r\nJust put it on yourself.\r\n\r\n##Usage\r\n* TODO Noto APIs\r\n* TODO Web Service\r\n* TODO Android End Device\r\n##Analysis\r\n\r\n###fields\r\n\r\n####單字\r\n* Id\r\n* word\r\n* roma\r\n* mean\r\n* english\r\n* Part of speech ( 如 自動 他動 第I類 名詞 形容詞等等)\r\n* Tag (其他特殊分類性質如 丁寧 常態 特殊發音，實作預設與自定義)\r\n* word formation (詞類變化紀錄)\r\n* relate word (同義詞 反義詞)\r\n* group (如 家具相關)\r\n* example 句子範例\r\n* situational (包含情況語氣，特殊含義等)\r\n\r\n####文法\r\n\r\n* Id\r\n* Sentence structure (自定義結構)\r\n* example 句子範例\r\n* group (如 否定相關)\r\n* situational (包含情況語氣，特殊含義等)\r\n","google":"","note":"Don't delete this file! It's used internally to help with page regeneration."}